opynfield/__init__.py
opynfield/calculate_measures/__init__.py
opynfield/calculate_measures/calculate_measures.py
opynfield/calculate_measures/coverage_math.py
opynfield/calculate_measures/standard_track.py
opynfield/config/__init__.py
opynfield/config/cov_asymptote.py
opynfield/config/defaults_settings.py
opynfield/config/model_settings.py
opynfield/config/plot_settings.py
opynfield/config/user_input.py
opynfield/fit_models/__init__.py
opynfield/fit_models/fit_group_models.py
opynfield/fit_models/fit_individual_models.py
opynfield/plotting/__init__.py
opynfield/plotting/plot_group_comparisons.py
opynfield/plotting/plot_individuals.py
opynfield/plotting/plot_solo_groups.py
opynfield/plotting/plot_solo_groups_with_individuals.py
opynfield/readin/__init__.py
opynfield/readin/anymaze_tracker.py
opynfield/readin/buridian_tracker.py
opynfield/readin/etho_tracker.py
opynfield/readin/multi_tracker.py
opynfield/readin/read_in.py
opynfield/readin/run_all.py
opynfield/readin/summary_file.py
opynfield/readin/track.py
opynfield/run.py
opynfield/stat_test/__init__.py
opynfield/stat_test/stat_test.py
opynfield/summarize_measures/__init__.py
opynfield/summarize_measures/summarize_groups.py
opynfield/summarize_measures/summarize_individuals.py
opynfield-1.0.0.dist-info/LICENSE
opynfield-1.0.0.dist-info/METADATA
opynfield-1.0.0.dist-info/WHEEL
opynfield-1.0.0.dist-info/RECORD
